[
    {
        "name": "Нержавеющая квадратная труба 20x20x2 мм AISI 304 EN 10210:2006 шлифованная теплодеформированная",
        "link": "https://exportural.kz/nerzhaveyushaya-kvadratnaya-truba/&page=1"
    },
    {
        "name": "Нержавеющая квадратная труба 20x20x2 AISI 304 EN 10210:2006 матовая холоднодеформированная",
        "link": "https://exportural.kz/nerzhaveyushaya-kvadratnaya-truba/&page=1"
    },
    {
        "name": "Нержавеющая квадратная труба 20x20x2 мм AISI 304 EN 10210:2006 зеркальная теплодеформированная",
        "link": "https://exportural.kz/nerzhaveyushaya-kvadratnaya-truba/&page=1"
    },
    {
        "name": "Нержавеющая квадратная труба 20x20x2 AISI 304 EN 10210:2006 шлифованная холоднодеформированная",
        "link": "https://exportural.kz/nerzhaveyushaya-kvadratnaya-truba/&page=1"
    },
    {
        "name": "Нержавеющая квадратная труба 25x25x2 мм AISI 304 EN 10210:2006 матовая теплодеформированная",
        "link": "https://exportural.kz/nerzhaveyushaya-kvadratnaya-truba/&page=1"
    },
    {
        "name": "Нержавеющая квадратная труба 25x25x2 AISI 304 EN 10210:2006 зеркальная холоднодеформированная",
        "link": "https://exportural.kz/nerzhaveyushaya-kvadratnaya-truba/&page=1"
    },
    {
        "name": "Нержавеющая квадратная труба 25x25x2 мм AISI 304 EN 10210:2006 шлифованная теплодеформированная",
        "link": "https://exportural.kz/nerzhaveyushaya-kvadratnaya-truba/&page=1"
    },
    {
        "name": "Нержавеющая квадратная труба 25x25x2 AISI 304 EN 10210:2006 матовая холоднодеформированная",
        "link": "https://exportural.kz/nerzhaveyushaya-kvadratnaya-truba/&page=1"
    },
    {
        "name": "Нержавеющая квадратная труба 25x25x3 мм AISI 304 EN 10210:2006 шлифованная теплодеформированная",
        "link": "https://exportural.kz/nerzhaveyushaya-kvadratnaya-truba/&page=1"
    },
    {
        "name": "Нержавеющая квадратная труба 25x25x3 AISI 304 EN 10210:2006 матовая холоднодеформированная",
        "link": "https://exportural.kz/nerzhaveyushaya-kvadratnaya-truba/&page=1"
    },
    {
        "name": "Нержавеющая квадратная труба 25x25x3 мм AISI 304 EN 10210:2006 зеркальная теплодеформированная",
        "link": "https://exportural.kz/nerzhaveyushaya-kvadratnaya-truba/&page=1"
    },
    {
        "name": "Нержавеющая квадратная труба 25x25x3 AISI 304 EN 10210:2006 шлифованная холоднодеформированная",
        "link": "https://exportural.kz/nerzhaveyushaya-kvadratnaya-truba/&page=1"
    },
    {
        "name": "Нержавеющая квадратная труба 40x40x2 мм AISI 304 EN 10210:2006 зеркальная теплодеформированная",
        "link": "https://exportural.kz/nerzhaveyushaya-kvadratnaya-truba/&page=1"
    },
    {
        "name": "Нержавеющая квадратная труба 40x40x2 AISI 304 EN 10210:2006 шлифованная холоднодеформированная",
        "link": "https://exportural.kz/nerzhaveyushaya-kvadratnaya-truba/&page=1"
    },
    {
        "name": "Нержавеющая квадратная труба 40x40x2 мм AISI 304 EN 10210:2006 матовая теплодеформированная",
        "link": "https://exportural.kz/nerzhaveyushaya-kvadratnaya-truba/&page=1"
    },
    {
        "name": "Нержавеющая квадратная труба 40x40x2 AISI 304 EN 10210:2006 зеркальная холоднодеформированная",
        "link": "https://exportural.kz/nerzhaveyushaya-kvadratnaya-truba/&page=2"
    },
    {
        "name": "Нержавеющая квадратная труба 40x40x3 мм AISI 304 EN 10210:2006 матовая теплодеформированная",
        "link": "https://exportural.kz/nerzhaveyushaya-kvadratnaya-truba/&page=2"
    },
    {
        "name": "Нержавеющая квадратная труба 40x40x3 AISI 304 EN 10210:2006 зеркальная холоднодеформированная",
        "link": "https://exportural.kz/nerzhaveyushaya-kvadratnaya-truba/&page=2"
    },
    {
        "name": "Нержавеющая квадратная труба 40x40x3 мм AISI 304 EN 10210:2006 шлифованная теплодеформированная",
        "link": "https://exportural.kz/nerzhaveyushaya-kvadratnaya-truba/&page=2"
    },
    {
        "name": "Нержавеющая квадратная труба 40x40x3 AISI 304 EN 10210:2006 матовая холоднодеформированная",
        "link": "https://exportural.kz/nerzhaveyushaya-kvadratnaya-truba/&page=2"
    },
    {
        "name": "Нержавеющая квадратная труба 40x40x4 мм AISI 304 EN 10210:2006 шлифованная теплодеформированная",
        "link": "https://exportural.kz/nerzhaveyushaya-kvadratnaya-truba/&page=2"
    },
    {
        "name": "Нержавеющая квадратная труба 40x40x4 AISI 304 EN 10210:2006 матовая холоднодеформированная",
        "link": "https://exportural.kz/nerzhaveyushaya-kvadratnaya-truba/&page=2"
    },
    {
        "name": "Нержавеющая квадратная труба 40x40x4 мм AISI 304 EN 10210:2006 зеркальная теплодеформированная",
        "link": "https://exportural.kz/nerzhaveyushaya-kvadratnaya-truba/&page=2"
    },
    {
        "name": "Нержавеющая квадратная труба 40x40x4 AISI 304 EN 10210:2006 шлифованная холоднодеформированная",
        "link": "https://exportural.kz/nerzhaveyushaya-kvadratnaya-truba/&page=2"
    },
    {
        "name": "Нержавеющая квадратная труба 50x50x2 мм AISI 304 EN 10210:2006 зеркальная теплодеформированная",
        "link": "https://exportural.kz/nerzhaveyushaya-kvadratnaya-truba/&page=2"
    },
    {
        "name": "Нержавеющая квадратная труба 50x50x2 AISI 304 EN 10210:2006 шлифованная холоднодеформированная",
        "link": "https://exportural.kz/nerzhaveyushaya-kvadratnaya-truba/&page=2"
    },
    {
        "name": "Нержавеющая квадратная труба 50x50x2 мм AISI 304 EN 10210:2006 матовая теплодеформированная",
        "link": "https://exportural.kz/nerzhaveyushaya-kvadratnaya-truba/&page=2"
    },
    {
        "name": "Нержавеющая квадратная труба 50x50x2 AISI 304 EN 10210:2006 зеркальная холоднодеформированная",
        "link": "https://exportural.kz/nerzhaveyushaya-kvadratnaya-truba/&page=2"
    },
    {
        "name": "Нержавеющая квадратная труба 50x50x3 мм AISI 304 EN 10210:2006 матовая теплодеформированная",
        "link": "https://exportural.kz/nerzhaveyushaya-kvadratnaya-truba/&page=2"
    },
    {
        "name": "Нержавеющая квадратная труба 50x50x3 AISI 304 EN 10210:2006 зеркальная холоднодеформированная",
        "link": "https://exportural.kz/nerzhaveyushaya-kvadratnaya-truba/&page=2"
    },
    {
        "name": "Нержавеющая квадратная труба 50x50x3 мм AISI 304 EN 10210:2006 шлифованная теплодеформированная",
        "link": "https://exportural.kz/nerzhaveyushaya-kvadratnaya-truba/&page=3"
    },
    {
        "name": "Нержавеющая квадратная труба 50x50x3 AISI 304 EN 10210:2006 матовая холоднодеформированная",
        "link": "https://exportural.kz/nerzhaveyushaya-kvadratnaya-truba/&page=3"
    },
    {
        "name": "Нержавеющая квадратная труба 50x50x4 мм AISI 304 EN 10210:2006 шлифованная теплодеформированная",
        "link": "https://exportural.kz/nerzhaveyushaya-kvadratnaya-truba/&page=3"
    },
    {
        "name": "Нержавеющая квадратная труба 50x50x4 AISI 304 EN 10210:2006 матовая холоднодеформированная",
        "link": "https://exportural.kz/nerzhaveyushaya-kvadratnaya-truba/&page=3"
    },
    {
        "name": "Нержавеющая квадратная труба 50x50x4 мм AISI 304 EN 10210:2006 зеркальная теплодеформированная",
        "link": "https://exportural.kz/nerzhaveyushaya-kvadratnaya-truba/&page=3"
    },
    {
        "name": "Нержавеющая квадратная труба 50x50x4 AISI 304 EN 10210:2006 шлифованная холоднодеформированная",
        "link": "https://exportural.kz/nerzhaveyushaya-kvadratnaya-truba/&page=3"
    },
    {
        "name": "Нержавеющая квадратная труба 10x10x0.8 мм 04Х18Н10 ГОСТ 8639-82 зеркальная",
        "link": "https://exportural.kz/nerzhaveyushaya-kvadratnaya-truba/&page=3"
    },
    {
        "name": "Нержавеющая квадратная труба 10x10x0.9 мм 04Х18Н10 ГОСТ 8639-82 шлифованная",
        "link": "https://exportural.kz/nerzhaveyushaya-kvadratnaya-truba/&page=3"
    },
    {
        "name": "Нержавеющая квадратная труба 10x10x1 мм 04Х18Н10 ГОСТ 8639-82 матовая",
        "link": "https://exportural.kz/nerzhaveyushaya-kvadratnaya-truba/&page=3"
    },
    {
        "name": "Нержавеющая квадратная труба 10x10x1.2 мм 04Х18Н10 ГОСТ 8639-82 зеркальная",
        "link": "https://exportural.kz/nerzhaveyushaya-kvadratnaya-truba/&page=3"
    },
    {
        "name": "Нержавеющая квадратная труба 10x10x1.4 мм 04Х18Н10 ГОСТ 8639-82 шлифованная",
        "link": "https://exportural.kz/nerzhaveyushaya-kvadratnaya-truba/&page=3"
    },
    {
        "name": "Нержавеющая квадратная труба 10x10x0.8 мм 06ХН28МДТ ГОСТ 8639-82 матовая",
        "link": "https://exportural.kz/nerzhaveyushaya-kvadratnaya-truba/&page=3"
    },
    {
        "name": "Нержавеющая квадратная труба 10x10x0.9 мм 06ХН28МДТ ГОСТ 8639-82 зеркальная",
        "link": "https://exportural.kz/nerzhaveyushaya-kvadratnaya-truba/&page=3"
    },
    {
        "name": "Нержавеющая квадратная труба 10x10x1 мм 06ХН28МДТ ГОСТ 8639-82 шлифованная",
        "link": "https://exportural.kz/nerzhaveyushaya-kvadratnaya-truba/&page=3"
    },
    {
        "name": "Нержавеющая квадратная труба 10x10x1.2 мм 06ХН28МДТ ГОСТ 8639-82 матовая",
        "link": "https://exportural.kz/nerzhaveyushaya-kvadratnaya-truba/&page=3"
    },
    {
        "name": "Нержавеющая квадратная труба 10x10x1.4 мм 06ХН28МДТ ГОСТ 8639-82 зеркальная",
        "link": "https://exportural.kz/nerzhaveyushaya-kvadratnaya-truba/&page=4"
    },
    {
        "name": "Нержавеющая квадратная труба 10x10x0.8 мм 08Х13 ГОСТ 8639-82 зеркальная",
        "link": "https://exportural.kz/nerzhaveyushaya-kvadratnaya-truba/&page=4"
    },
    {
        "name": "Нержавеющая квадратная труба 10x10x0.9 мм 08Х13 ГОСТ 8639-82 шлифованная",
        "link": "https://exportural.kz/nerzhaveyushaya-kvadratnaya-truba/&page=4"
    },
    {
        "name": "Нержавеющая квадратная труба 10x10x1 мм 08Х13 ГОСТ 8639-82 матовая",
        "link": "https://exportural.kz/nerzhaveyushaya-kvadratnaya-truba/&page=4"
    },
    {
        "name": "Нержавеющая квадратная труба 10x10x1.2 мм 08Х13 ГОСТ 8639-82 зеркальная",
        "link": "https://exportural.kz/nerzhaveyushaya-kvadratnaya-truba/&page=4"
    },
    {
        "name": "Нержавеющая квадратная труба 10x10x1.4 мм 08Х13 ГОСТ 8639-82 шлифованная",
        "link": "https://exportural.kz/nerzhaveyushaya-kvadratnaya-truba/&page=4"
    },
    {
        "name": "Нержавеющая квадратная труба 10x10x0.8 мм 08Х17Н15М3Т ГОСТ 8639-82 шлифованная",
        "link": "https://exportural.kz/nerzhaveyushaya-kvadratnaya-truba/&page=4"
    },
    {
        "name": "Нержавеющая квадратная труба 10x10x0.9 мм 08Х17Н15М3Т ГОСТ 8639-82 матовая",
        "link": "https://exportural.kz/nerzhaveyushaya-kvadratnaya-truba/&page=4"
    },
    {
        "name": "Нержавеющая квадратная труба 10x10x1 мм 08Х17Н15М3Т ГОСТ 8639-82 зеркальная",
        "link": "https://exportural.kz/nerzhaveyushaya-kvadratnaya-truba/&page=4"
    },
    {
        "name": "Нержавеющая квадратная труба 10x10x1.2 мм 08Х17Н15М3Т ГОСТ 8639-82 шлифованная",
        "link": "https://exportural.kz/nerzhaveyushaya-kvadratnaya-truba/&page=4"
    },
    {
        "name": "Нержавеющая квадратная труба 10x10x1.4 мм 08Х17Н15М3Т ГОСТ 8639-82 матовая",
        "link": "https://exportural.kz/nerzhaveyushaya-kvadratnaya-truba/&page=4"
    },
    {
        "name": "Нержавеющая квадратная труба 10x10x0.8 мм 08Х17Т ГОСТ 8639-82 матовая",
        "link": "https://exportural.kz/nerzhaveyushaya-kvadratnaya-truba/&page=4"
    },
    {
        "name": "Нержавеющая квадратная труба 10x10x0.9 мм 08Х17Т ГОСТ 8639-82 зеркальная",
        "link": "https://exportural.kz/nerzhaveyushaya-kvadratnaya-truba/&page=4"
    },
    {
        "name": "Нержавеющая квадратная труба 10x10x1 мм 08Х17Т ГОСТ 8639-82 шлифованная",
        "link": "https://exportural.kz/nerzhaveyushaya-kvadratnaya-truba/&page=4"
    },
    {
        "name": "Нержавеющая квадратная труба 10x10x1.2 мм 08Х17Т ГОСТ 8639-82 матовая",
        "link": "https://exportural.kz/nerzhaveyushaya-kvadratnaya-truba/&page=4"
    },
    {
        "name": "Нержавеющая квадратная труба 10x10x1.4 мм 08Х17Т ГОСТ 8639-82 зеркальная",
        "link": "https://exportural.kz/nerzhaveyushaya-kvadratnaya-truba/&page=5"
    },
    {
        "name": "Нержавеющая квадратная труба 10x10x0.8 мм 08Х18Н10 ГОСТ 8639-82 зеркальная",
        "link": "https://exportural.kz/nerzhaveyushaya-kvadratnaya-truba/&page=5"
    },
    {
        "name": "Нержавеющая квадратная труба 10x10x0.9 мм 08Х18Н10 ГОСТ 8639-82 шлифованная",
        "link": "https://exportural.kz/nerzhaveyushaya-kvadratnaya-truba/&page=5"
    },
    {
        "name": "Нержавеющая квадратная труба 10x10x1 мм 08Х18Н10 ГОСТ 8639-82 матовая",
        "link": "https://exportural.kz/nerzhaveyushaya-kvadratnaya-truba/&page=5"
    },
    {
        "name": "Нержавеющая квадратная труба 10x10x1.2 мм 08Х18Н10 ГОСТ 8639-82 зеркальная",
        "link": "https://exportural.kz/nerzhaveyushaya-kvadratnaya-truba/&page=5"
    },
    {
        "name": "Нержавеющая квадратная труба 10x10x1.4 мм 08Х18Н10 ГОСТ 8639-82 шлифованная",
        "link": "https://exportural.kz/nerzhaveyushaya-kvadratnaya-truba/&page=5"
    },
    {
        "name": "Нержавеющая квадратная труба 10x10x0.8 мм 08Х18Н10Т ГОСТ 8639-82 матовая",
        "link": "https://exportural.kz/nerzhaveyushaya-kvadratnaya-truba/&page=5"
    },
    {
        "name": "Нержавеющая квадратная труба 10x10x0.9 мм 08Х18Н10Т ГОСТ 8639-82 зеркальная",
        "link": "https://exportural.kz/nerzhaveyushaya-kvadratnaya-truba/&page=5"
    },
    {
        "name": "Нержавеющая квадратная труба 10x10x1 мм 08Х18Н10Т ГОСТ 8639-82 шлифованная",
        "link": "https://exportural.kz/nerzhaveyushaya-kvadratnaya-truba/&page=5"
    },
    {
        "name": "Нержавеющая квадратная труба 10x10x1.2 мм 08Х18Н10Т ГОСТ 8639-82 матовая",
        "link": "https://exportural.kz/nerzhaveyushaya-kvadratnaya-truba/&page=5"
    },
    {
        "name": "Нержавеющая квадратная труба 10x10x1.4 мм 08Х18Н10Т ГОСТ 8639-82 зеркальная",
        "link": "https://exportural.kz/nerzhaveyushaya-kvadratnaya-truba/&page=5"
    },
    {
        "name": "Нержавеющая квадратная труба 10x10x0.8 мм 08Х18Н12Б ГОСТ 8639-82 шлифованная",
        "link": "https://exportural.kz/nerzhaveyushaya-kvadratnaya-truba/&page=5"
    },
    {
        "name": "Нержавеющая квадратная труба 10x10x0.9 мм 08Х18Н12Б ГОСТ 8639-82 матовая",
        "link": "https://exportural.kz/nerzhaveyushaya-kvadratnaya-truba/&page=5"
    },
    {
        "name": "Нержавеющая квадратная труба 10x10x1 мм 08Х18Н12Б ГОСТ 8639-82 зеркальная",
        "link": "https://exportural.kz/nerzhaveyushaya-kvadratnaya-truba/&page=5"
    },
    {
        "name": "Нержавеющая квадратная труба 10x10x1.2 мм 08Х18Н12Б ГОСТ 8639-82 шлифованная",
        "link": "https://exportural.kz/nerzhaveyushaya-kvadratnaya-truba/&page=5"
    },
    {
        "name": "Нержавеющая квадратная труба 10x10x1.4 мм 08Х18Н12Б ГОСТ 8639-82 матовая",
        "link": "https://exportural.kz/nerzhaveyushaya-kvadratnaya-truba/&page=6"
    },
    {
        "name": "Нержавеющая квадратная труба 10x10x0.8 мм 08Х18Н12Т ГОСТ 8639-82 зеркальная",
        "link": "https://exportural.kz/nerzhaveyushaya-kvadratnaya-truba/&page=6"
    },
    {
        "name": "Нержавеющая квадратная труба 10x10x0.9 мм 08Х18Н12Т ГОСТ 8639-82 шлифованная",
        "link": "https://exportural.kz/nerzhaveyushaya-kvadratnaya-truba/&page=6"
    },
    {
        "name": "Нержавеющая квадратная труба 10x10x1 мм 08Х18Н12Т ГОСТ 8639-82 матовая",
        "link": "https://exportural.kz/nerzhaveyushaya-kvadratnaya-truba/&page=6"
    },
    {
        "name": "Нержавеющая квадратная труба 10x10x1.2 мм 08Х18Н12Т ГОСТ 8639-82 зеркальная",
        "link": "https://exportural.kz/nerzhaveyushaya-kvadratnaya-truba/&page=6"
    },
    {
        "name": "Нержавеющая квадратная труба 10x10x1.4 мм 08Х18Н12Т ГОСТ 8639-82 шлифованная",
        "link": "https://exportural.kz/nerzhaveyushaya-kvadratnaya-truba/&page=6"
    },
    {
        "name": "Нержавеющая квадратная труба 10x10x0.8 мм 08Х20Н14С2 ГОСТ 8639-82 матовая",
        "link": "https://exportural.kz/nerzhaveyushaya-kvadratnaya-truba/&page=6"
    },
    {
        "name": "Нержавеющая квадратная труба 10x10x0.9 мм 08Х20Н14С2 ГОСТ 8639-82 зеркальная",
        "link": "https://exportural.kz/nerzhaveyushaya-kvadratnaya-truba/&page=6"
    },
    {
        "name": "Нержавеющая квадратная труба 10x10x1 мм 08Х20Н14С2 ГОСТ 8639-82 шлифованная",
        "link": "https://exportural.kz/nerzhaveyushaya-kvadratnaya-truba/&page=6"
    },
    {
        "name": "Нержавеющая квадратная труба 10x10x1.2 мм 08Х20Н14С2 ГОСТ 8639-82 матовая",
        "link": "https://exportural.kz/nerzhaveyushaya-kvadratnaya-truba/&page=6"
    },
    {
        "name": "Нержавеющая квадратная труба 10x10x1.4 мм 08Х20Н14С2 ГОСТ 8639-82 зеркальная",
        "link": "https://exportural.kz/nerzhaveyushaya-kvadratnaya-truba/&page=6"
    },
    {
        "name": "Нержавеющая квадратная труба 10x10x0.8 мм 08Х22Н6Т ГОСТ 8639-82 матовая",
        "link": "https://exportural.kz/nerzhaveyushaya-kvadratnaya-truba/&page=6"
    },
    {
        "name": "Нержавеющая квадратная труба 10x10x0.9 мм 08Х22Н6Т ГОСТ 8639-82 зеркальная",
        "link": "https://exportural.kz/nerzhaveyushaya-kvadratnaya-truba/&page=6"
    },
    {
        "name": "Нержавеющая квадратная труба 10x10x1 мм 08Х22Н6Т ГОСТ 8639-82 шлифованная",
        "link": "https://exportural.kz/nerzhaveyushaya-kvadratnaya-truba/&page=6"
    },
    {
        "name": "Нержавеющая квадратная труба 10x10x1.2 мм 08Х22Н6Т ГОСТ 8639-82 матовая",
        "link": "https://exportural.kz/nerzhaveyushaya-kvadratnaya-truba/&page=6"
    },
    {
        "name": "Нержавеющая квадратная труба 10x10x1.4 мм 08Х22Н6Т ГОСТ 8639-82 зеркальная",
        "link": "https://exportural.kz/nerzhaveyushaya-kvadratnaya-truba/&page=7"
    },
    {
        "name": "Нержавеющая квадратная труба 10x10x0.8 мм 10Х17Н13М2Т ГОСТ 8639-82 шлифованная",
        "link": "https://exportural.kz/nerzhaveyushaya-kvadratnaya-truba/&page=7"
    },
    {
        "name": "Нержавеющая квадратная труба 10x10x0.9 мм 10Х17Н13М2Т ГОСТ 8639-82 матовая",
        "link": "https://exportural.kz/nerzhaveyushaya-kvadratnaya-truba/&page=7"
    },
    {
        "name": "Нержавеющая квадратная труба 10x10x1 мм 10Х17Н13М2Т ГОСТ 8639-82 зеркальная",
        "link": "https://exportural.kz/nerzhaveyushaya-kvadratnaya-truba/&page=7"
    },
    {
        "name": "Нержавеющая квадратная труба 10x10x1.2 мм 10Х17Н13М2Т ГОСТ 8639-82 шлифованная",
        "link": "https://exportural.kz/nerzhaveyushaya-kvadratnaya-truba/&page=7"
    },
    {
        "name": "Нержавеющая квадратная труба 10x10x1.4 мм 10Х17Н13М2Т ГОСТ 8639-82 матовая",
        "link": "https://exportural.kz/nerzhaveyushaya-kvadratnaya-truba/&page=7"
    },
    {
        "name": "Нержавеющая квадратная труба 10x10x0.8 мм 10Х23Н18 ГОСТ 8639-82 матовая",
        "link": "https://exportural.kz/nerzhaveyushaya-kvadratnaya-truba/&page=7"
    },
    {
        "name": "Нержавеющая квадратная труба 10x10x0.9 мм 10Х23Н18 ГОСТ 8639-82 зеркальная",
        "link": "https://exportural.kz/nerzhaveyushaya-kvadratnaya-truba/&page=7"
    },
    {
        "name": "Нержавеющая квадратная труба 10x10x1 мм 10Х23Н18 ГОСТ 8639-82 шлифованная",
        "link": "https://exportural.kz/nerzhaveyushaya-kvadratnaya-truba/&page=7"
    },
    {
        "name": "Нержавеющая квадратная труба 10x10x1.2 мм 10Х23Н18 ГОСТ 8639-82 матовая",
        "link": "https://exportural.kz/nerzhaveyushaya-kvadratnaya-truba/&page=7"
    },
    {
        "name": "Нержавеющая квадратная труба 10x10x1.4 мм 10Х23Н18 ГОСТ 8639-82 зеркальная",
        "link": "https://exportural.kz/nerzhaveyushaya-kvadratnaya-truba/&page=7"
    },
    {
        "name": "Нержавеющая квадратная труба 10x10x0.8 мм 12Х13 ГОСТ 8639-82 шлифованная",
        "link": "https://exportural.kz/nerzhaveyushaya-kvadratnaya-truba/&page=7"
    },
    {
        "name": "Нержавеющая квадратная труба 10x10x0.9 мм 12Х13 ГОСТ 8639-82 матовая",
        "link": "https://exportural.kz/nerzhaveyushaya-kvadratnaya-truba/&page=7"
    },
    {
        "name": "Нержавеющая квадратная труба 10x10x1 мм 12Х13 ГОСТ 8639-82 зеркальная",
        "link": "https://exportural.kz/nerzhaveyushaya-kvadratnaya-truba/&page=7"
    },
    {
        "name": "Нержавеющая квадратная труба 10x10x1.2 мм 12Х13 ГОСТ 8639-82 шлифованная",
        "link": "https://exportural.kz/nerzhaveyushaya-kvadratnaya-truba/&page=7"
    },
    {
        "name": "Нержавеющая квадратная труба 10x10x1.4 мм 12Х13 ГОСТ 8639-82 матовая",
        "link": "https://exportural.kz/nerzhaveyushaya-kvadratnaya-truba/&page=8"
    },
    {
        "name": "Нержавеющая квадратная труба 10x10x0.8 мм 12Х17 ГОСТ 8639-82 зеркальная",
        "link": "https://exportural.kz/nerzhaveyushaya-kvadratnaya-truba/&page=8"
    },
    {
        "name": "Нержавеющая квадратная труба 10x10x0.9 мм 12Х17 ГОСТ 8639-82 шлифованная",
        "link": "https://exportural.kz/nerzhaveyushaya-kvadratnaya-truba/&page=8"
    },
    {
        "name": "Нержавеющая квадратная труба 10x10x1 мм 12Х17 ГОСТ 8639-82 матовая",
        "link": "https://exportural.kz/nerzhaveyushaya-kvadratnaya-truba/&page=8"
    },
    {
        "name": "Нержавеющая квадратная труба 10x10x1.2 мм 12Х17 ГОСТ 8639-82 зеркальная",
        "link": "https://exportural.kz/nerzhaveyushaya-kvadratnaya-truba/&page=8"
    },
    {
        "name": "Нержавеющая квадратная труба 10x10x1.4 мм 12Х17 ГОСТ 8639-82 шлифованная",
        "link": "https://exportural.kz/nerzhaveyushaya-kvadratnaya-truba/&page=8"
    },
    {
        "name": "Нержавеющая квадратная труба 10x10x0.8 мм 12Х18Н10Т ГОСТ 8639-82 матовая",
        "link": "https://exportural.kz/nerzhaveyushaya-kvadratnaya-truba/&page=8"
    },
    {
        "name": "Нержавеющая квадратная труба 10x10x0.9 мм 12Х18Н10Т ГОСТ 8639-82 зеркальная",
        "link": "https://exportural.kz/nerzhaveyushaya-kvadratnaya-truba/&page=8"
    },
    {
        "name": "Нержавеющая квадратная труба 10x10x1 мм 12Х18Н10Т ГОСТ 8639-82 шлифованная",
        "link": "https://exportural.kz/nerzhaveyushaya-kvadratnaya-truba/&page=8"
    },
    {
        "name": "Нержавеющая квадратная труба 10x10x1.2 мм 12Х18Н10Т ГОСТ 8639-82 матовая",
        "link": "https://exportural.kz/nerzhaveyushaya-kvadratnaya-truba/&page=8"
    },
    {
        "name": "Нержавеющая квадратная труба 10x10x1.4 мм 12Х18Н10Т ГОСТ 8639-82 зеркальная",
        "link": "https://exportural.kz/nerzhaveyushaya-kvadratnaya-truba/&page=8"
    },
    {
        "name": "Нержавеющая квадратная труба 10x10x0.8 мм 12Х18Н12Т ГОСТ 8639-82 шлифованная",
        "link": "https://exportural.kz/nerzhaveyushaya-kvadratnaya-truba/&page=8"
    },
    {
        "name": "Нержавеющая квадратная труба 10x10x0.9 мм 12Х18Н12Т ГОСТ 8639-82 матовая",
        "link": "https://exportural.kz/nerzhaveyushaya-kvadratnaya-truba/&page=8"
    },
    {
        "name": "Нержавеющая квадратная труба 10x10x1 мм 12Х18Н12Т ГОСТ 8639-82 зеркальная",
        "link": "https://exportural.kz/nerzhaveyushaya-kvadratnaya-truba/&page=8"
    },
    {
        "name": "Нержавеющая квадратная труба 10x10x1.2 мм 12Х18Н12Т ГОСТ 8639-82 шлифованная",
        "link": "https://exportural.kz/nerzhaveyushaya-kvadratnaya-truba/&page=8"
    },
    {
        "name": "Нержавеющая квадратная труба 10x10x1.4 мм 12Х18Н12Т ГОСТ 8639-82 матовая",
        "link": "https://exportural.kz/nerzhaveyushaya-kvadratnaya-truba/&page=9"
    },
    {
        "name": "Нержавеющая квадратная труба 10x10x0.8 мм 12Х18Н9 ГОСТ 8639-82 зеркальная",
        "link": "https://exportural.kz/nerzhaveyushaya-kvadratnaya-truba/&page=9"
    },
    {
        "name": "Нержавеющая квадратная труба 10x10x0.9 мм 12Х18Н9 ГОСТ 8639-82 шлифованная",
        "link": "https://exportural.kz/nerzhaveyushaya-kvadratnaya-truba/&page=9"
    },
    {
        "name": "Нержавеющая квадратная труба 10x10x1 мм 12Х18Н9 ГОСТ 8639-82 матовая",
        "link": "https://exportural.kz/nerzhaveyushaya-kvadratnaya-truba/&page=9"
    },
    {
        "name": "Нержавеющая квадратная труба 10x10x1.2 мм 12Х18Н9 ГОСТ 8639-82 зеркальная",
        "link": "https://exportural.kz/nerzhaveyushaya-kvadratnaya-truba/&page=9"
    },
    {
        "name": "Нержавеющая квадратная труба 10x10x1.4 мм 12Х18Н9 ГОСТ 8639-82 шлифованная",
        "link": "https://exportural.kz/nerzhaveyushaya-kvadratnaya-truba/&page=9"
    },
    {
        "name": "Нержавеющая квадратная труба 10x10x0.8 мм 15Х25Т ГОСТ 8639-82 шлифованная",
        "link": "https://exportural.kz/nerzhaveyushaya-kvadratnaya-truba/&page=9"
    },
    {
        "name": "Нержавеющая квадратная труба 10x10x0.9 мм 15Х25Т ГОСТ 8639-82 матовая",
        "link": "https://exportural.kz/nerzhaveyushaya-kvadratnaya-truba/&page=9"
    },
    {
        "name": "Нержавеющая квадратная труба 10x10x1 мм 15Х25Т ГОСТ 8639-82 зеркальная",
        "link": "https://exportural.kz/nerzhaveyushaya-kvadratnaya-truba/&page=9"
    },
    {
        "name": "Нержавеющая квадратная труба 10x10x1.2 мм 15Х25Т ГОСТ 8639-82 шлифованная",
        "link": "https://exportural.kz/nerzhaveyushaya-kvadratnaya-truba/&page=9"
    },
    {
        "name": "Нержавеющая квадратная труба 10x10x1.4 мм 15Х25Т ГОСТ 8639-82 матовая",
        "link": "https://exportural.kz/nerzhaveyushaya-kvadratnaya-truba/&page=9"
    },
    {
        "name": "Нержавеющая квадратная труба 10x10x0.8 мм 17Х18Н9 ГОСТ 8639-82 зеркальная",
        "link": "https://exportural.kz/nerzhaveyushaya-kvadratnaya-truba/&page=9"
    },
    {
        "name": "Нержавеющая квадратная труба 10x10x0.9 мм 17Х18Н9 ГОСТ 8639-82 шлифованная",
        "link": "https://exportural.kz/nerzhaveyushaya-kvadratnaya-truba/&page=9"
    },
    {
        "name": "Нержавеющая квадратная труба 10x10x1 мм 17Х18Н9 ГОСТ 8639-82 матовая",
        "link": "https://exportural.kz/nerzhaveyushaya-kvadratnaya-truba/&page=9"
    },
    {
        "name": "Нержавеющая квадратная труба 10x10x1.2 мм 17Х18Н9 ГОСТ 8639-82 зеркальная",
        "link": "https://exportural.kz/nerzhaveyushaya-kvadratnaya-truba/&page=9"
    },
    {
        "name": "Нержавеющая квадратная труба 10x10x1.4 мм 17Х18Н9 ГОСТ 8639-82 шлифованная",
        "link": "https://exportural.kz/nerzhaveyushaya-kvadratnaya-truba/&page=10"
    },
    {
        "name": "Нержавеющая квадратная труба 10x10x0,8 AISI 201 EN 10210:2006 зеркальная холоднодеформированная",
        "link": "https://exportural.kz/nerzhaveyushaya-kvadratnaya-truba/&page=10"
    },
    {
        "name": "Нержавеющая квадратная труба 10x10x0,8 мм AISI 201 EN 10210:2006 шлифованная теплодеформированная",
        "link": "https://exportural.kz/nerzhaveyushaya-kvadratnaya-truba/&page=10"
    },
    {
        "name": "Нержавеющая квадратная труба 10x10x0,8 AISI 201 EN 10210:2006 матовая холоднодеформированная",
        "link": "https://exportural.kz/nerzhaveyushaya-kvadratnaya-truba/&page=10"
    },
    {
        "name": "Нержавеющая квадратная труба 10x10x0,8 мм AISI 201 EN 10210:2006 зеркальная теплодеформированная",
        "link": "https://exportural.kz/nerzhaveyushaya-kvadratnaya-truba/&page=10"
    },
    {
        "name": "Нержавеющая квадратная труба 10x10x0,9 AISI 201 EN 10210:2006 шлифованная холоднодеформированная",
        "link": "https://exportural.kz/nerzhaveyushaya-kvadratnaya-truba/&page=10"
    },
    {
        "name": "Нержавеющая квадратная труба 10x10x0,9 мм AISI 201 EN 10210:2006 матовая теплодеформированная",
        "link": "https://exportural.kz/nerzhaveyushaya-kvadratnaya-truba/&page=10"
    },
    {
        "name": "Нержавеющая квадратная труба 10x10x0,9 AISI 201 EN 10210:2006 зеркальная холоднодеформированная",
        "link": "https://exportural.kz/nerzhaveyushaya-kvadratnaya-truba/&page=10"
    },
    {
        "name": "Нержавеющая квадратная труба 10x10x0,9 мм AISI 201 EN 10210:2006 шлифованная теплодеформированная",
        "link": "https://exportural.kz/nerzhaveyushaya-kvadratnaya-truba/&page=10"
    },
    {
        "name": "Нержавеющая квадратная труба 10x10x1 AISI 201 EN 10210:2006 матовая холоднодеформированная",
        "link": "https://exportural.kz/nerzhaveyushaya-kvadratnaya-truba/&page=10"
    },
    {
        "name": "Нержавеющая квадратная труба 10x10x1 мм AISI 201 EN 10210:2006 зеркальная теплодеформированная",
        "link": "https://exportural.kz/nerzhaveyushaya-kvadratnaya-truba/&page=10"
    },
    {
        "name": "Нержавеющая квадратная труба 10x10x1 AISI 201 EN 10210:2006 шлифованная холоднодеформированная",
        "link": "https://exportural.kz/nerzhaveyushaya-kvadratnaya-truba/&page=10"
    },
    {
        "name": "Нержавеющая квадратная труба 10x10x1 мм AISI 201 EN 10210:2006 матовая теплодеформированная",
        "link": "https://exportural.kz/nerzhaveyushaya-kvadratnaya-truba/&page=10"
    },
    {
        "name": "Нержавеющая квадратная труба 10x10x1,2 AISI 201 EN 10210:2006 зеркальная холоднодеформированная",
        "link": "https://exportural.kz/nerzhaveyushaya-kvadratnaya-truba/&page=10"
    },
    {
        "name": "Нержавеющая квадратная труба 10x10x1,2 мм AISI 201 EN 10210:2006 шлифованная теплодеформированная",
        "link": "https://exportural.kz/nerzhaveyushaya-kvadratnaya-truba/&page=10"
    },
    {
        "name": "Нержавеющая квадратная труба 10x10x1,2 AISI 201 EN 10210:2006 матовая холоднодеформированная",
        "link": "https://exportural.kz/nerzhaveyushaya-kvadratnaya-truba/&page=11"
    },
    {
        "name": "Нержавеющая квадратная труба 10x10x1,2 мм AISI 201 EN 10210:2006 зеркальная теплодеформированная",
        "link": "https://exportural.kz/nerzhaveyushaya-kvadratnaya-truba/&page=11"
    },
    {
        "name": "Нержавеющая квадратная труба 10x10x1,4 AISI 201 EN 10210:2006 шлифованная холоднодеформированная",
        "link": "https://exportural.kz/nerzhaveyushaya-kvadratnaya-truba/&page=11"
    },
    {
        "name": "Нержавеющая квадратная труба 10x10x1,4 мм AISI 201 EN 10210:2006 матовая теплодеформированная",
        "link": "https://exportural.kz/nerzhaveyushaya-kvadratnaya-truba/&page=11"
    },
    {
        "name": "Нержавеющая квадратная труба 10x10x1,4 AISI 201 EN 10210:2006 зеркальная холоднодеформированная",
        "link": "https://exportural.kz/nerzhaveyushaya-kvadratnaya-truba/&page=11"
    },
    {
        "name": "Нержавеющая квадратная труба 10x10x1,4 мм AISI 201 EN 10210:2006 шлифованная теплодеформированная",
        "link": "https://exportural.kz/nerzhaveyushaya-kvadratnaya-truba/&page=11"
    },
    {
        "name": "Нержавеющая квадратная труба 10x10x0,8 мм AISI 304 EN 10210:2006 матовая теплодеформированная",
        "link": "https://exportural.kz/nerzhaveyushaya-kvadratnaya-truba/&page=11"
    },
    {
        "name": "Нержавеющая квадратная труба 10x10x0,8 AISI 304 EN 10210:2006 зеркальная холоднодеформированная",
        "link": "https://exportural.kz/nerzhaveyushaya-kvadratnaya-truba/&page=11"
    },
    {
        "name": "Нержавеющая квадратная труба 10x10x0,8 мм AISI 304 EN 10210:2006 шлифованная теплодеформированная",
        "link": "https://exportural.kz/nerzhaveyushaya-kvadratnaya-truba/&page=11"
    },
    {
        "name": "Нержавеющая квадратная труба 10x10x0,8 AISI 304 EN 10210:2006 матовая холоднодеформированная",
        "link": "https://exportural.kz/nerzhaveyushaya-kvadratnaya-truba/&page=11"
    },
    {
        "name": "Нержавеющая квадратная труба 10x10x0,9 мм AISI 304 EN 10210:2006 зеркальная теплодеформированная",
        "link": "https://exportural.kz/nerzhaveyushaya-kvadratnaya-truba/&page=11"
    },
    {
        "name": "Нержавеющая квадратная труба 10x10x0,9 AISI 304 EN 10210:2006 шлифованная холоднодеформированная",
        "link": "https://exportural.kz/nerzhaveyushaya-kvadratnaya-truba/&page=11"
    },
    {
        "name": "Нержавеющая квадратная труба 10x10x0,9 мм AISI 304 EN 10210:2006 матовая теплодеформированная",
        "link": "https://exportural.kz/nerzhaveyushaya-kvadratnaya-truba/&page=11"
    },
    {
        "name": "Нержавеющая квадратная труба 10x10x0,9 AISI 304 EN 10210:2006 зеркальная холоднодеформированная",
        "link": "https://exportural.kz/nerzhaveyushaya-kvadratnaya-truba/&page=11"
    },
    {
        "name": "Нержавеющая квадратная труба 10x10x1 мм AISI 304 EN 10210:2006 шлифованная теплодеформированная",
        "link": "https://exportural.kz/nerzhaveyushaya-kvadratnaya-truba/&page=11"
    },
    {
        "name": "Нержавеющая квадратная труба 10x10x1 AISI 304 EN 10210:2006 матовая холоднодеформированная",
        "link": "https://exportural.kz/nerzhaveyushaya-kvadratnaya-truba/&page=12"
    },
    {
        "name": "Нержавеющая квадратная труба 10x10x1 мм AISI 304 EN 10210:2006 зеркальная теплодеформированная",
        "link": "https://exportural.kz/nerzhaveyushaya-kvadratnaya-truba/&page=12"
    },
    {
        "name": "Нержавеющая квадратная труба 10x10x1 AISI 304 EN 10210:2006 шлифованная холоднодеформированная",
        "link": "https://exportural.kz/nerzhaveyushaya-kvadratnaya-truba/&page=12"
    },
    {
        "name": "Нержавеющая квадратная труба 10x10x1,2 мм AISI 304 EN 10210:2006 матовая теплодеформированная",
        "link": "https://exportural.kz/nerzhaveyushaya-kvadratnaya-truba/&page=12"
    },
    {
        "name": "Нержавеющая квадратная труба 10x10x1,2 AISI 304 EN 10210:2006 зеркальная холоднодеформированная",
        "link": "https://exportural.kz/nerzhaveyushaya-kvadratnaya-truba/&page=12"
    },
    {
        "name": "Нержавеющая квадратная труба 10x10x1,2 мм AISI 304 EN 10210:2006 шлифованная теплодеформированная",
        "link": "https://exportural.kz/nerzhaveyushaya-kvadratnaya-truba/&page=12"
    },
    {
        "name": "Нержавеющая квадратная труба 10x10x1,2 AISI 304 EN 10210:2006 матовая холоднодеформированная",
        "link": "https://exportural.kz/nerzhaveyushaya-kvadratnaya-truba/&page=12"
    },
    {
        "name": "Нержавеющая квадратная труба 10x10x1,4 мм AISI 304 EN 10210:2006 зеркальная теплодеформированная",
        "link": "https://exportural.kz/nerzhaveyushaya-kvadratnaya-truba/&page=12"
    },
    {
        "name": "Нержавеющая квадратная труба 10x10x1,4 AISI 304 EN 10210:2006 шлифованная холоднодеформированная",
        "link": "https://exportural.kz/nerzhaveyushaya-kvadratnaya-truba/&page=12"
    },
    {
        "name": "Нержавеющая квадратная труба 10x10x1,4 мм AISI 304 EN 10210:2006 матовая теплодеформированная",
        "link": "https://exportural.kz/nerzhaveyushaya-kvadratnaya-truba/&page=12"
    },
    {
        "name": "Нержавеющая квадратная труба 10x10x1,4 AISI 304 EN 10210:2006 зеркальная холоднодеформированная",
        "link": "https://exportural.kz/nerzhaveyushaya-kvadratnaya-truba/&page=12"
    },
    {
        "name": "Нержавеющая квадратная труба 10x10x0,8 AISI 316L EN 10210:2006 шлифованная холоднодеформированная",
        "link": "https://exportural.kz/nerzhaveyushaya-kvadratnaya-truba/&page=12"
    },
    {
        "name": "Нержавеющая квадратная труба 10x10x0,8 мм AISI 316L EN 10210:2006 матовая теплодеформированная",
        "link": "https://exportural.kz/nerzhaveyushaya-kvadratnaya-truba/&page=12"
    },
    {
        "name": "Нержавеющая квадратная труба 10x10x0,8 AISI 316L EN 10210:2006 зеркальная холоднодеформированная",
        "link": "https://exportural.kz/nerzhaveyushaya-kvadratnaya-truba/&page=12"
    },
    {
        "name": "Нержавеющая квадратная труба 10x10x0,8 мм AISI 316L EN 10210:2006 шлифованная теплодеформированная",
        "link": "https://exportural.kz/nerzhaveyushaya-kvadratnaya-truba/&page=12"
    },
    {
        "name": "Нержавеющая квадратная труба 10x10x0,9 AISI 316L EN 10210:2006 матовая холоднодеформированная",
        "link": "https://exportural.kz/nerzhaveyushaya-kvadratnaya-truba/&page=13"
    },
    {
        "name": "Нержавеющая квадратная труба 10x10x0,9 мм AISI 316L EN 10210:2006 зеркальная теплодеформированная",
        "link": "https://exportural.kz/nerzhaveyushaya-kvadratnaya-truba/&page=13"
    },
    {
        "name": "Нержавеющая квадратная труба 10x10x0,9 AISI 316L EN 10210:2006 шлифованная холоднодеформированная",
        "link": "https://exportural.kz/nerzhaveyushaya-kvadratnaya-truba/&page=13"
    },
    {
        "name": "Нержавеющая квадратная труба 10x10x0,9 мм AISI 316L EN 10210:2006 матовая теплодеформированная",
        "link": "https://exportural.kz/nerzhaveyushaya-kvadratnaya-truba/&page=13"
    },
    {
        "name": "Нержавеющая квадратная труба 10x10x1 AISI 316L EN 10210:2006 зеркальная холоднодеформированная",
        "link": "https://exportural.kz/nerzhaveyushaya-kvadratnaya-truba/&page=13"
    },
    {
        "name": "Нержавеющая квадратная труба 10x10x1 мм AISI 316L EN 10210:2006 шлифованная теплодеформированная",
        "link": "https://exportural.kz/nerzhaveyushaya-kvadratnaya-truba/&page=13"
    },
    {
        "name": "Нержавеющая квадратная труба 10x10x1 AISI 316L EN 10210:2006 матовая холоднодеформированная",
        "link": "https://exportural.kz/nerzhaveyushaya-kvadratnaya-truba/&page=13"
    },
    {
        "name": "Нержавеющая квадратная труба 10x10x1 мм AISI 316L EN 10210:2006 зеркальная теплодеформированная",
        "link": "https://exportural.kz/nerzhaveyushaya-kvadratnaya-truba/&page=13"
    },
    {
        "name": "Нержавеющая квадратная труба 10x10x1,2 AISI 316L EN 10210:2006 шлифованная холоднодеформированная",
        "link": "https://exportural.kz/nerzhaveyushaya-kvadratnaya-truba/&page=13"
    },
    {
        "name": "Нержавеющая квадратная труба 10x10x1,2 мм AISI 316L EN 10210:2006 матовая теплодеформированная",
        "link": "https://exportural.kz/nerzhaveyushaya-kvadratnaya-truba/&page=13"
    },
    {
        "name": "Нержавеющая квадратная труба 10x10x1,2 AISI 316L EN 10210:2006 зеркальная холоднодеформированная",
        "link": "https://exportural.kz/nerzhaveyushaya-kvadratnaya-truba/&page=13"
    },
    {
        "name": "Нержавеющая квадратная труба 10x10x1,2 мм AISI 316L EN 10210:2006 шлифованная теплодеформированная",
        "link": "https://exportural.kz/nerzhaveyushaya-kvadratnaya-truba/&page=13"
    },
    {
        "name": "Нержавеющая квадратная труба 10x10x1,4 AISI 316L EN 10210:2006 матовая холоднодеформированная",
        "link": "https://exportural.kz/nerzhaveyushaya-kvadratnaya-truba/&page=13"
    },
    {
        "name": "Нержавеющая квадратная труба 10x10x1,4 мм AISI 316L EN 10210:2006 зеркальная теплодеформированная",
        "link": "https://exportural.kz/nerzhaveyushaya-kvadratnaya-truba/&page=13"
    },
    {
        "name": "Нержавеющая квадратная труба 10x10x1,4 AISI 316L EN 10210:2006 шлифованная холоднодеформированная",
        "link": "https://exportural.kz/nerzhaveyushaya-kvadratnaya-truba/&page=13"
    },
    {
        "name": "Нержавеющая квадратная труба 10x10x1,4 мм AISI 316L EN 10210:2006 матовая теплодеформированная",
        "link": "https://exportural.kz/nerzhaveyushaya-kvadratnaya-truba/&page=14"
    },
    {
        "name": "Нержавеющая квадратная труба 10x10x0,8 мм AISI 316Ti EN 10210:2006 зеркальная теплодеформированная",
        "link": "https://exportural.kz/nerzhaveyushaya-kvadratnaya-truba/&page=14"
    },
    {
        "name": "Нержавеющая квадратная труба 10x10x0,8 AISI 316Ti EN 10210:2006 шлифованная холоднодеформированная",
        "link": "https://exportural.kz/nerzhaveyushaya-kvadratnaya-truba/&page=14"
    },
    {
        "name": "Нержавеющая квадратная труба 10x10x0,8 мм AISI 316Ti EN 10210:2006 матовая теплодеформированная",
        "link": "https://exportural.kz/nerzhaveyushaya-kvadratnaya-truba/&page=14"
    },
    {
        "name": "Нержавеющая квадратная труба 10x10x0,8 AISI 316Ti EN 10210:2006 зеркальная холоднодеформированная",
        "link": "https://exportural.kz/nerzhaveyushaya-kvadratnaya-truba/&page=14"
    },
    {
        "name": "Нержавеющая квадратная труба 10x10x0,9 мм AISI 316Ti EN 10210:2006 шлифованная теплодеформированная",
        "link": "https://exportural.kz/nerzhaveyushaya-kvadratnaya-truba/&page=14"
    },
    {
        "name": "Нержавеющая квадратная труба 10x10x0,9 AISI 316Ti EN 10210:2006 матовая холоднодеформированная",
        "link": "https://exportural.kz/nerzhaveyushaya-kvadratnaya-truba/&page=14"
    },
    {
        "name": "Нержавеющая квадратная труба 10x10x0,9 мм AISI 316Ti EN 10210:2006 зеркальная теплодеформированная",
        "link": "https://exportural.kz/nerzhaveyushaya-kvadratnaya-truba/&page=14"
    },
    {
        "name": "Нержавеющая квадратная труба 10x10x0,9 AISI 316Ti EN 10210:2006 шлифованная холоднодеформированная",
        "link": "https://exportural.kz/nerzhaveyushaya-kvadratnaya-truba/&page=14"
    },
    {
        "name": "Нержавеющая квадратная труба 10x10x1 мм AISI 316Ti EN 10210:2006 матовая теплодеформированная",
        "link": "https://exportural.kz/nerzhaveyushaya-kvadratnaya-truba/&page=14"
    },
    {
        "name": "Нержавеющая квадратная труба 10x10x1 AISI 316Ti EN 10210:2006 зеркальная холоднодеформированная",
        "link": "https://exportural.kz/nerzhaveyushaya-kvadratnaya-truba/&page=14"
    },
    {
        "name": "Нержавеющая квадратная труба 10x10x1 мм AISI 316Ti EN 10210:2006 шлифованная теплодеформированная",
        "link": "https://exportural.kz/nerzhaveyushaya-kvadratnaya-truba/&page=14"
    },
    {
        "name": "Нержавеющая квадратная труба 10x10x1 AISI 316Ti EN 10210:2006 матовая холоднодеформированная",
        "link": "https://exportural.kz/nerzhaveyushaya-kvadratnaya-truba/&page=14"
    },
    {
        "name": "Нержавеющая квадратная труба 10x10x1,2 мм AISI 316Ti EN 10210:2006 зеркальная теплодеформированная",
        "link": "https://exportural.kz/nerzhaveyushaya-kvadratnaya-truba/&page=14"
    },
    {
        "name": "Нержавеющая квадратная труба 10x10x1,2 AISI 316Ti EN 10210:2006 шлифованная холоднодеформированная",
        "link": "https://exportural.kz/nerzhaveyushaya-kvadratnaya-truba/&page=14"
    },
    {
        "name": "Нержавеющая квадратная труба 10x10x1,2 мм AISI 316Ti EN 10210:2006 матовая теплодеформированная",
        "link": "https://exportural.kz/nerzhaveyushaya-kvadratnaya-truba/&page=15"
    },
    {
        "name": "Нержавеющая квадратная труба 10x10x1,2 AISI 316Ti EN 10210:2006 зеркальная холоднодеформированная",
        "link": "https://exportural.kz/nerzhaveyushaya-kvadratnaya-truba/&page=15"
    },
    {
        "name": "Нержавеющая квадратная труба 10x10x1,4 мм AISI 316Ti EN 10210:2006 шлифованная теплодеформированная",
        "link": "https://exportural.kz/nerzhaveyushaya-kvadratnaya-truba/&page=15"
    },
    {
        "name": "Нержавеющая квадратная труба 10x10x1,4 AISI 316Ti EN 10210:2006 матовая холоднодеформированная",
        "link": "https://exportural.kz/nerzhaveyushaya-kvadratnaya-truba/&page=15"
    },
    {
        "name": "Нержавеющая квадратная труба 10x10x1,4 мм AISI 316Ti EN 10210:2006 зеркальная теплодеформированная",
        "link": "https://exportural.kz/nerzhaveyushaya-kvadratnaya-truba/&page=15"
    },
    {
        "name": "Нержавеющая квадратная труба 10x10x1,4 AISI 316Ti EN 10210:2006 шлифованная холоднодеформированная",
        "link": "https://exportural.kz/nerzhaveyushaya-kvadratnaya-truba/&page=15"
    },
    {
        "name": "Нержавеющая квадратная труба 10x10x0,8 AISI 430 EN 10210:2006 матовая холоднодеформированная",
        "link": "https://exportural.kz/nerzhaveyushaya-kvadratnaya-truba/&page=15"
    },
    {
        "name": "Нержавеющая квадратная труба 10x10x0,8 мм AISI 430 EN 10210:2006 зеркальная теплодеформированная",
        "link": "https://exportural.kz/nerzhaveyushaya-kvadratnaya-truba/&page=15"
    },
    {
        "name": "Нержавеющая квадратная труба 10x10x0,8 AISI 430 EN 10210:2006 шлифованная холоднодеформированная",
        "link": "https://exportural.kz/nerzhaveyushaya-kvadratnaya-truba/&page=15"
    },
    {
        "name": "Нержавеющая квадратная труба 10x10x0,8 мм AISI 430 EN 10210:2006 матовая теплодеформированная",
        "link": "https://exportural.kz/nerzhaveyushaya-kvadratnaya-truba/&page=15"
    },
    {
        "name": "Нержавеющая квадратная труба 10x10x0,9 AISI 430 EN 10210:2006 зеркальная холоднодеформированная",
        "link": "https://exportural.kz/nerzhaveyushaya-kvadratnaya-truba/&page=15"
    },
    {
        "name": "Нержавеющая квадратная труба 10x10x0,9 мм AISI 430 EN 10210:2006 шлифованная теплодеформированная",
        "link": "https://exportural.kz/nerzhaveyushaya-kvadratnaya-truba/&page=15"
    },
    {
        "name": "Нержавеющая квадратная труба 10x10x0,9 AISI 430 EN 10210:2006 матовая холоднодеформированная",
        "link": "https://exportural.kz/nerzhaveyushaya-kvadratnaya-truba/&page=15"
    },
    {
        "name": "Нержавеющая квадратная труба 10x10x0,9 мм AISI 430 EN 10210:2006 зеркальная теплодеформированная",
        "link": "https://exportural.kz/nerzhaveyushaya-kvadratnaya-truba/&page=15"
    },
    {
        "name": "Нержавеющая квадратная труба 10x10x1 AISI 430 EN 10210:2006 шлифованная холоднодеформированная",
        "link": "https://exportural.kz/nerzhaveyushaya-kvadratnaya-truba/&page=15"
    },
    {
        "name": "Нержавеющая квадратная труба 10x10x1 мм AISI 430 EN 10210:2006 матовая теплодеформированная",
        "link": "https://exportural.kz/nerzhaveyushaya-kvadratnaya-truba/&page=16"
    },
    {
        "name": "Нержавеющая квадратная труба 10x10x1 AISI 430 EN 10210:2006 зеркальная холоднодеформированная",
        "link": "https://exportural.kz/nerzhaveyushaya-kvadratnaya-truba/&page=16"
    },
    {
        "name": "Нержавеющая квадратная труба 10x10x1 мм AISI 430 EN 10210:2006 шлифованная теплодеформированная",
        "link": "https://exportural.kz/nerzhaveyushaya-kvadratnaya-truba/&page=16"
    },
    {
        "name": "Нержавеющая квадратная труба 10x10x1,2 AISI 430 EN 10210:2006 матовая холоднодеформированная",
        "link": "https://exportural.kz/nerzhaveyushaya-kvadratnaya-truba/&page=16"
    },
    {
        "name": "Нержавеющая квадратная труба 10x10x1,2 мм AISI 430 EN 10210:2006 зеркальная теплодеформированная",
        "link": "https://exportural.kz/nerzhaveyushaya-kvadratnaya-truba/&page=16"
    },
    {
        "name": "Нержавеющая квадратная труба 10x10x1,2 AISI 430 EN 10210:2006 шлифованная холоднодеформированная",
        "link": "https://exportural.kz/nerzhaveyushaya-kvadratnaya-truba/&page=16"
    },
    {
        "name": "Нержавеющая квадратная труба 10x10x1,2 мм AISI 430 EN 10210:2006 матовая теплодеформированная",
        "link": "https://exportural.kz/nerzhaveyushaya-kvadratnaya-truba/&page=16"
    },
    {
        "name": "Нержавеющая квадратная труба 10x10x1,4 AISI 430 EN 10210:2006 зеркальная холоднодеформированная",
        "link": "https://exportural.kz/nerzhaveyushaya-kvadratnaya-truba/&page=16"
    },
    {
        "name": "Нержавеющая квадратная труба 10x10x1,4 мм AISI 430 EN 10210:2006 шлифованная теплодеформированная",
        "link": "https://exportural.kz/nerzhaveyushaya-kvadratnaya-truba/&page=16"
    },
    {
        "name": "Нержавеющая квадратная труба 10x10x1,4 AISI 430 EN 10210:2006 матовая холоднодеформированная",
        "link": "https://exportural.kz/nerzhaveyushaya-kvadratnaya-truba/&page=16"
    },
    {
        "name": "Нержавеющая квадратная труба 10x10x1,4 мм AISI 430 EN 10210:2006 зеркальная теплодеформированная",
        "link": "https://exportural.kz/nerzhaveyushaya-kvadratnaya-truba/&page=16"
    },
    {
        "name": "Нержавеющая квадратная труба 15x15x0.8 мм 04Х18Н10 ГОСТ 8639-82 матовая",
        "link": "https://exportural.kz/nerzhaveyushaya-kvadratnaya-truba/&page=16"
    },
    {
        "name": "Нержавеющая квадратная труба 15x15x0.9 мм 04Х18Н10 ГОСТ 8639-82 зеркальная",
        "link": "https://exportural.kz/nerzhaveyushaya-kvadratnaya-truba/&page=16"
    },
    {
        "name": "Нержавеющая квадратная труба 15x15x1 мм 04Х18Н10 ГОСТ 8639-82 шлифованная",
        "link": "https://exportural.kz/nerzhaveyushaya-kvadratnaya-truba/&page=16"
    },
    {
        "name": "Нержавеющая квадратная труба 15x15x1.2 мм 04Х18Н10 ГОСТ 8639-82 матовая",
        "link": "https://exportural.kz/nerzhaveyushaya-kvadratnaya-truba/&page=16"
    },
    {
        "name": "Нержавеющая квадратная труба 15x15x1.4 мм 04Х18Н10 ГОСТ 8639-82 зеркальная",
        "link": "https://exportural.kz/nerzhaveyushaya-kvadratnaya-truba/&page=17"
    },
    {
        "name": "Нержавеющая квадратная труба 15x15x1.5 мм 04Х18Н10 ГОСТ 8639-82 шлифованная",
        "link": "https://exportural.kz/nerzhaveyushaya-kvadratnaya-truba/&page=17"
    },
    {
        "name": "Нержавеющая квадратная труба 15x15x0.8 мм 06ХН28МДТ ГОСТ 8639-82 шлифованная",
        "link": "https://exportural.kz/nerzhaveyushaya-kvadratnaya-truba/&page=17"
    },
    {
        "name": "Нержавеющая квадратная труба 15x15x0.9 мм 06ХН28МДТ ГОСТ 8639-82 матовая",
        "link": "https://exportural.kz/nerzhaveyushaya-kvadratnaya-truba/&page=17"
    },
    {
        "name": "Нержавеющая квадратная труба 15x15x1 мм 06ХН28МДТ ГОСТ 8639-82 зеркальная",
        "link": "https://exportural.kz/nerzhaveyushaya-kvadratnaya-truba/&page=17"
    },
    {
        "name": "Нержавеющая квадратная труба 15x15x1.2 мм 06ХН28МДТ ГОСТ 8639-82 шлифованная",
        "link": "https://exportural.kz/nerzhaveyushaya-kvadratnaya-truba/&page=17"
    },
    {
        "name": "Нержавеющая квадратная труба 15x15x1.4 мм 06ХН28МДТ ГОСТ 8639-82 матовая",
        "link": "https://exportural.kz/nerzhaveyushaya-kvadratnaya-truba/&page=17"
    },
    {
        "name": "Нержавеющая квадратная труба 15x15x1.5 мм 06ХН28МДТ ГОСТ 8639-82 зеркальная",
        "link": "https://exportural.kz/nerzhaveyushaya-kvadratnaya-truba/&page=17"
    },
    {
        "name": "Нержавеющая квадратная труба 15x15x0.8 мм 08Х13 ГОСТ 8639-82 матовая",
        "link": "https://exportural.kz/nerzhaveyushaya-kvadratnaya-truba/&page=17"
    },
    {
        "name": "Нержавеющая квадратная труба 15x15x0.9 мм 08Х13 ГОСТ 8639-82 зеркальная",
        "link": "https://exportural.kz/nerzhaveyushaya-kvadratnaya-truba/&page=17"
    },
    {
        "name": "Нержавеющая квадратная труба 15x15x1 мм 08Х13 ГОСТ 8639-82 шлифованная",
        "link": "https://exportural.kz/nerzhaveyushaya-kvadratnaya-truba/&page=17"
    },
    {
        "name": "Нержавеющая квадратная труба 15x15x1.2 мм 08Х13 ГОСТ 8639-82 матовая",
        "link": "https://exportural.kz/nerzhaveyushaya-kvadratnaya-truba/&page=17"
    },
    {
        "name": "Нержавеющая квадратная труба 15x15x1.4 мм 08Х13 ГОСТ 8639-82 зеркальная",
        "link": "https://exportural.kz/nerzhaveyushaya-kvadratnaya-truba/&page=17"
    },
    {
        "name": "Нержавеющая квадратная труба 15x15x1.5 мм 08Х13 ГОСТ 8639-82 шлифованная",
        "link": "https://exportural.kz/nerzhaveyushaya-kvadratnaya-truba/&page=17"
    },
    {
        "name": "Нержавеющая квадратная труба 15x15x0.8 мм 08Х17Н15М3Т ГОСТ 8639-82 зеркальная",
        "link": "https://exportural.kz/nerzhaveyushaya-kvadratnaya-truba/&page=17"
    },
    {
        "name": "Нержавеющая квадратная труба 15x15x0.9 мм 08Х17Н15М3Т ГОСТ 8639-82 шлифованная",
        "link": "https://exportural.kz/nerzhaveyushaya-kvadratnaya-truba/&page=18"
    },
    {
        "name": "Нержавеющая квадратная труба 15x15x1 мм 08Х17Н15М3Т ГОСТ 8639-82 матовая",
        "link": "https://exportural.kz/nerzhaveyushaya-kvadratnaya-truba/&page=18"
    },
    {
        "name": "Нержавеющая квадратная труба 15x15x1.2 мм 08Х17Н15М3Т ГОСТ 8639-82 зеркальная",
        "link": "https://exportural.kz/nerzhaveyushaya-kvadratnaya-truba/&page=18"
    },
    {
        "name": "Нержавеющая квадратная труба 15x15x1.4 мм 08Х17Н15М3Т ГОСТ 8639-82 шлифованная",
        "link": "https://exportural.kz/nerzhaveyushaya-kvadratnaya-truba/&page=18"
    },
    {
        "name": "Нержавеющая квадратная труба 15x15x1.5 мм 08Х17Н15М3Т ГОСТ 8639-82 матовая",
        "link": "https://exportural.kz/nerzhaveyushaya-kvadratnaya-truba/&page=18"
    },
    {
        "name": "Нержавеющая квадратная труба 15x15x0.8 мм 08Х17Т ГОСТ 8639-82 шлифованная",
        "link": "https://exportural.kz/nerzhaveyushaya-kvadratnaya-truba/&page=18"
    },
    {
        "name": "Нержавеющая квадратная труба 15x15x0.9 мм 08Х17Т ГОСТ 8639-82 матовая",
        "link": "https://exportural.kz/nerzhaveyushaya-kvadratnaya-truba/&page=18"
    },
    {
        "name": "Нержавеющая квадратная труба 15x15x1 мм 08Х17Т ГОСТ 8639-82 зеркальная",
        "link": "https://exportural.kz/nerzhaveyushaya-kvadratnaya-truba/&page=18"
    },
    {
        "name": "Нержавеющая квадратная труба 15x15x1.2 мм 08Х17Т ГОСТ 8639-82 шлифованная",
        "link": "https://exportural.kz/nerzhaveyushaya-kvadratnaya-truba/&page=18"
    },
    {
        "name": "Нержавеющая квадратная труба 15x15x1.4 мм 08Х17Т ГОСТ 8639-82 матовая",
        "link": "https://exportural.kz/nerzhaveyushaya-kvadratnaya-truba/&page=18"
    },
    {
        "name": "Нержавеющая квадратная труба 15x15x1.5 мм 08Х17Т ГОСТ 8639-82 зеркальная",
        "link": "https://exportural.kz/nerzhaveyushaya-kvadratnaya-truba/&page=18"
    },
    {
        "name": "Нержавеющая квадратная труба 15x15x0.8 мм 08Х18Н10 ГОСТ 8639-82 матовая",
        "link": "https://exportural.kz/nerzhaveyushaya-kvadratnaya-truba/&page=18"
    },
    {
        "name": "Нержавеющая квадратная труба 15x15x0.9 мм 08Х18Н10 ГОСТ 8639-82 зеркальная",
        "link": "https://exportural.kz/nerzhaveyushaya-kvadratnaya-truba/&page=18"
    },
    {
        "name": "Нержавеющая квадратная труба 15x15x1 мм 08Х18Н10 ГОСТ 8639-82 шлифованная",
        "link": "https://exportural.kz/nerzhaveyushaya-kvadratnaya-truba/&page=18"
    },
    {
        "name": "Нержавеющая квадратная труба 15x15x1.2 мм 08Х18Н10 ГОСТ 8639-82 матовая",
        "link": "https://exportural.kz/nerzhaveyushaya-kvadratnaya-truba/&page=18"
    },
    {
        "name": "Нержавеющая квадратная труба 15x15x1.4 мм 08Х18Н10 ГОСТ 8639-82 зеркальная",
        "link": "https://exportural.kz/nerzhaveyushaya-kvadratnaya-truba/&page=19"
    },
    {
        "name": "Нержавеющая квадратная труба 15x15x1.5 мм 08Х18Н10 ГОСТ 8639-82 шлифованная",
        "link": "https://exportural.kz/nerzhaveyushaya-kvadratnaya-truba/&page=19"
    },
    {
        "name": "Нержавеющая квадратная труба 15x15x0.8 мм 08Х18Н10Т ГОСТ 8639-82 шлифованная",
        "link": "https://exportural.kz/nerzhaveyushaya-kvadratnaya-truba/&page=19"
    },
    {
        "name": "Нержавеющая квадратная труба 15x15x0.9 мм 08Х18Н10Т ГОСТ 8639-82 матовая",
        "link": "https://exportural.kz/nerzhaveyushaya-kvadratnaya-truba/&page=19"
    },
    {
        "name": "Нержавеющая квадратная труба 15x15x1 мм 08Х18Н10Т ГОСТ 8639-82 зеркальная",
        "link": "https://exportural.kz/nerzhaveyushaya-kvadratnaya-truba/&page=19"
    },
    {
        "name": "Нержавеющая квадратная труба 15x15x1.2 мм 08Х18Н10Т ГОСТ 8639-82 шлифованная",
        "link": "https://exportural.kz/nerzhaveyushaya-kvadratnaya-truba/&page=19"
    },
    {
        "name": "Нержавеющая квадратная труба 15x15x1.4 мм 08Х18Н10Т ГОСТ 8639-82 матовая",
        "link": "https://exportural.kz/nerzhaveyushaya-kvadratnaya-truba/&page=19"
    },
    {
        "name": "Нержавеющая квадратная труба 15x15x1.5 мм 08Х18Н10Т ГОСТ 8639-82 зеркальная",
        "link": "https://exportural.kz/nerzhaveyushaya-kvadratnaya-truba/&page=19"
    },
    {
        "name": "Нержавеющая квадратная труба 15x15x0.8 мм 08Х18Н12Б ГОСТ 8639-82 зеркальная",
        "link": "https://exportural.kz/nerzhaveyushaya-kvadratnaya-truba/&page=19"
    },
    {
        "name": "Нержавеющая квадратная труба 15x15x0.9 мм 08Х18Н12Б ГОСТ 8639-82 шлифованная",
        "link": "https://exportural.kz/nerzhaveyushaya-kvadratnaya-truba/&page=19"
    },
    {
        "name": "Нержавеющая квадратная труба 15x15x1 мм 08Х18Н12Б ГОСТ 8639-82 матовая",
        "link": "https://exportural.kz/nerzhaveyushaya-kvadratnaya-truba/&page=19"
    },
    {
        "name": "Нержавеющая квадратная труба 15x15x1.2 мм 08Х18Н12Б ГОСТ 8639-82 зеркальная",
        "link": "https://exportural.kz/nerzhaveyushaya-kvadratnaya-truba/&page=19"
    },
    {
        "name": "Нержавеющая квадратная труба 15x15x1.4 мм 08Х18Н12Б ГОСТ 8639-82 шлифованная",
        "link": "https://exportural.kz/nerzhaveyushaya-kvadratnaya-truba/&page=19"
    },
    {
        "name": "Нержавеющая квадратная труба 15x15x1.5 мм 08Х18Н12Б ГОСТ 8639-82 матовая",
        "link": "https://exportural.kz/nerzhaveyushaya-kvadratnaya-truba/&page=19"
    },
    {
        "name": "Нержавеющая квадратная труба 15x15x0.8 мм 08Х18Н12Т ГОСТ 8639-82 матовая",
        "link": "https://exportural.kz/nerzhaveyushaya-kvadratnaya-truba/&page=19"
    },
    {
        "name": "Нержавеющая квадратная труба 15x15x0.9 мм 08Х18Н12Т ГОСТ 8639-82 зеркальная",
        "link": "https://exportural.kz/nerzhaveyushaya-kvadratnaya-truba/&page=20"
    },
    {
        "name": "Нержавеющая квадратная труба 15x15x1 мм 08Х18Н12Т ГОСТ 8639-82 шлифованная",
        "link": "https://exportural.kz/nerzhaveyushaya-kvadratnaya-truba/&page=20"
    },
    {
        "name": "Нержавеющая квадратная труба 15x15x1.2 мм 08Х18Н12Т ГОСТ 8639-82 матовая",
        "link": "https://exportural.kz/nerzhaveyushaya-kvadratnaya-truba/&page=20"
    },
    {
        "name": "Нержавеющая квадратная труба 15x15x1.4 мм 08Х18Н12Т ГОСТ 8639-82 зеркальная",
        "link": "https://exportural.kz/nerzhaveyushaya-kvadratnaya-truba/&page=20"
    },
    {
        "name": "Нержавеющая квадратная труба 15x15x1.5 мм 08Х18Н12Т ГОСТ 8639-82 шлифованная",
        "link": "https://exportural.kz/nerzhaveyushaya-kvadratnaya-truba/&page=20"
    },
    {
        "name": "Нержавеющая квадратная труба 15x15x0.8 мм 08Х20Н14С2 ГОСТ 8639-82 шлифованная",
        "link": "https://exportural.kz/nerzhaveyushaya-kvadratnaya-truba/&page=20"
    },
    {
        "name": "Нержавеющая квадратная труба 15x15x0.9 мм 08Х20Н14С2 ГОСТ 8639-82 матовая",
        "link": "https://exportural.kz/nerzhaveyushaya-kvadratnaya-truba/&page=20"
    },
    {
        "name": "Нержавеющая квадратная труба 15x15x1 мм 08Х20Н14С2 ГОСТ 8639-82 зеркальная",
        "link": "https://exportural.kz/nerzhaveyushaya-kvadratnaya-truba/&page=20"
    },
    {
        "name": "Нержавеющая квадратная труба 15x15x1.2 мм 08Х20Н14С2 ГОСТ 8639-82 шлифованная",
        "link": "https://exportural.kz/nerzhaveyushaya-kvadratnaya-truba/&page=20"
    },
    {
        "name": "Нержавеющая квадратная труба 15x15x1.4 мм 08Х20Н14С2 ГОСТ 8639-82 матовая",
        "link": "https://exportural.kz/nerzhaveyushaya-kvadratnaya-truba/&page=20"
    },
    {
        "name": "Нержавеющая квадратная труба 15x15x1.5 мм 08Х20Н14С2 ГОСТ 8639-82 зеркальная",
        "link": "https://exportural.kz/nerzhaveyushaya-kvadratnaya-truba/&page=20"
    },
    {
        "name": "Нержавеющая квадратная труба 15x15x0.8 мм 08Х22Н6Т ГОСТ 8639-82 шлифованная",
        "link": "https://exportural.kz/nerzhaveyushaya-kvadratnaya-truba/&page=20"
    },
    {
        "name": "Нержавеющая квадратная труба 15x15x0.9 мм 08Х22Н6Т ГОСТ 8639-82 матовая",
        "link": "https://exportural.kz/nerzhaveyushaya-kvadratnaya-truba/&page=20"
    },
    {
        "name": "Нержавеющая квадратная труба 15x15x1 мм 08Х22Н6Т ГОСТ 8639-82 зеркальная",
        "link": "https://exportural.kz/nerzhaveyushaya-kvadratnaya-truba/&page=20"
    },
    {
        "name": "Нержавеющая квадратная труба 15x15x1.2 мм 08Х22Н6Т ГОСТ 8639-82 шлифованная",
        "link": "https://exportural.kz/nerzhaveyushaya-kvadratnaya-truba/&page=20"
    }
]